MANIFEST.in
README.rst
setup.py
drf_chaos/__init__.py
drf_chaos/decorators.py
drf_chaos/middleware.py
drf_chaos/settings.py
drf_chaos.egg-info/PKG-INFO
drf_chaos.egg-info/SOURCES.txt
drf_chaos.egg-info/dependency_links.txt
drf_chaos.egg-info/not-zip-safe
drf_chaos.egg-info/requires.txt
drf_chaos.egg-info/top_level.txt