Metadata-Version: 1.1
Name: drf-chaos
Version: 0.1.3
Summary: Collection of decorators and middlewares for testing DRF API under unexpected circumstances.
Home-page: https://github.com/aledista/drf-chaos
Author: Alessio Di Stasio
Author-email: aledista@gmail.com
License: BSD
Platform: UNKNOWN
Classifier: Development Status :: 4 - Beta
Classifier: Environment :: Web Environment
Classifier: Intended Audience :: Developers
Classifier: License :: OSI Approved :: BSD License
Classifier: Operating System :: OS Independent
Classifier: Programming Language :: Python
